{
	"testScenarioName": "px.pims.sepa.add.success",
	"responsesPerApiCall": {
		"addPI": {
			"statusCode": 200,
			"content": {"id":"Sge3ZwAAAAABAACA","accountId":"e0ac2a98-9473-4a32-bfe9-ee7b1dce16c0","paymentMethod":{"paymentMethodType":"sepa","properties":{"offlineRecurring":true,"userManaged":true,"soldToAddressRequired":true,"splitPaymentSupported":false,"supportedOperations":["charge","refund","chargeback","credit","settlementReversal"],"taxable":false,"providerRemittable":false},"exclusionTags":["LegacySubscriptions","Perpetual","PhysicalGoods"],"paymentMethodFamily":"direct_debit","display":{"name":"Direct debit","logo":"https://pmservices.cp.microsoft.com/staticresourceservice/images/V4/Logo_SEPA.png","logos":[{"mimeType":"image/png","url":"https://pmservices.cp.microsoft.com/staticresourceservice/images/V4/Logo_SEPA.png"},{"mimeType":"image/svg+xml","url":"https://pmservices.cp.microsoft.com/staticresourceservice/images/v4/logo_sepa.svg"}]}},"status":"Pending","creationDateTime":"2017-04-12T23:13:07.987","lastUpdatedDateTime":"2017-04-12T23:13:07.987","details":{"pendingOn":"Redirect","exportable":false,"accountHolderName":"Swaroop","address":{"address_line1":"Post Bank","city":"Berlin","postal_code":"10866","country":"DE"},"lastFourDigits":"7113","redirectUrl":"https://pmservices.cp.microsoft.com/RedirectionService/CoreRedirection/Redirect/fa350f25-b8d8-e0c8-4c54-566e744082c7","picvRequired":true}}
		},
		"getPI": {
			"statusCode": 200,
			"content": {"id":"Sge3ZwAAAAABAACA","accountId":"e0ac2a98-9473-4a32-bfe9-ee7b1dce16c0","paymentMethod":{"paymentMethodType":"sepa","properties":{"offlineRecurring":true,"userManaged":true,"soldToAddressRequired":true,"splitPaymentSupported":false,"supportedOperations":["charge","refund","chargeback","credit","settlementReversal"],"taxable":false,"providerRemittable":false},"exclusionTags":["LegacySubscriptions","Perpetual","PhysicalGoods"],"paymentMethodFamily":"direct_debit","display":{"name":"Direct debit","logo":"https://pmservices.cp.microsoft.com/staticresourceservice/images/V4/Logo_SEPA.png","logos":[{"mimeType":"image/png","url":"https://pmservices.cp.microsoft.com/staticresourceservice/images/V4/Logo_SEPA.png"},{"mimeType":"image/svg+xml","url":"https://pmservices.cp.microsoft.com/staticresourceservice/images/v4/logo_sepa.svg"}]}},"status":"Active","creationDateTime":"2017-04-12T23:13:07.987","lastUpdatedDateTime":"2017-04-12T23:13:07.987","details":{"picvDetails":{"status":"inProgress","remainingAttempts":"3"},"exportable":false,"accountHolderName":"Swaroop","address":{"address_line1":"Post Bank","city":"Berlin","postal_code":"10866","country":"DE"},"lastFourDigits":"7113","redirectUrl":"https://pmservices.cp.microsoft.com/RedirectionService/CoreRedirection/Redirect/fa350f25-b8d8-e0c8-4c54-566e744082c7","picvRequired":true}}
		},
		"getPM": {
			"statusCode": 200,
			"content": [{"paymentMethodFamily":"direct_debit","paymentMethodType":"sepa","display":{"name":"Sepa","logo":"https://pmservices.cp.microsoft.com/staticresourceservice/images/V4/Logo_SEPA.png","logos":[{"mimeType":"image/png","url":"https://pmservices.cp.microsoft.com/staticresourceservice/images/V4/Logo_SEPA.png"},{"mimeType":"image/svg+xml","url":"https://pmservices.cp.microsoft.com/staticresourceservice/images/v4/logo_sepa.svg"}]},"properties":{"offlineRecurring":true,"userManaged":true,"soldToAddressRequired":true,"supportedOperations":["charge","refund","chargeback","credit","settlementReversal"],"taxable":false,"providerRemittable":false,"moBillingIdentityUrl":"","riskyPaymentMethod":true,"fundsAvailabilityWindow":14400,"multipleLineItemsSupported":true,"splitPaymentSupported":false,"purchaseWaitTime":0,"redirectRequired":["Add"]},"exclusionTags":["LegacySubscriptions","Perpetual","PhysicalGoods"]}]
		}
	}
}
